gllm_datastore.cpython-312-darwin.so
gllm_datastore.pyi
gllm_datastore/__init__.pyi
gllm_datastore/constants.pyi
gllm_datastore/cache/__init__.pyi
gllm_datastore/cache/base.pyi
gllm_datastore/cache/cache.pyi
gllm_datastore/cache/utils.pyi
gllm_datastore/cache/hybrid_cache/__init__.pyi
gllm_datastore/cache/hybrid_cache/file_system_hybrid_cache.pyi
gllm_datastore/cache/hybrid_cache/hybrid_cache.pyi
gllm_datastore/cache/hybrid_cache/in_memory_hybrid_cache.pyi
gllm_datastore/cache/hybrid_cache/redis_hybrid_cache.pyi
gllm_datastore/cache/hybrid_cache/utils.pyi
gllm_datastore/cache/hybrid_cache/key_matcher/__init__.pyi
gllm_datastore/cache/hybrid_cache/key_matcher/exact_key_matcher.pyi
gllm_datastore/cache/hybrid_cache/key_matcher/fuzzy_key_matcher.pyi
gllm_datastore/cache/hybrid_cache/key_matcher/key_matcher.pyi
gllm_datastore/cache/hybrid_cache/key_matcher/semantic_key_matcher.pyi
gllm_datastore/cache/vector_cache/__init__.pyi
gllm_datastore/cache/vector_cache/vector_cache.pyi
gllm_datastore/cache/vector_cache/eviction_manager/__init__.pyi
gllm_datastore/cache/vector_cache/eviction_manager/asyncio_eviction_manager.pyi
gllm_datastore/cache/vector_cache/eviction_manager/eviction_manager.pyi
gllm_datastore/cache/vector_cache/eviction_strategy/__init__.pyi
gllm_datastore/cache/vector_cache/eviction_strategy/eviction_strategy.pyi
gllm_datastore/cache/vector_cache/eviction_strategy/ttl_eviction_strategy.pyi
gllm_datastore/core/__init__.pyi
gllm_datastore/core/capabilities/__init__.pyi
gllm_datastore/core/capabilities/encryption_capability.pyi
gllm_datastore/core/capabilities/fulltext_capability.pyi
gllm_datastore/core/capabilities/graph_capability.pyi
gllm_datastore/core/capabilities/hybrid_capability.pyi
gllm_datastore/core/capabilities/vector_capability.pyi
gllm_datastore/core/filters/__init__.pyi
gllm_datastore/core/filters/filter.pyi
gllm_datastore/core/filters/schema.pyi
gllm_datastore/data_store/__init__.pyi
gllm_datastore/data_store/base.pyi
gllm_datastore_binary-0.5.56.dist-info/METADATA
gllm_datastore_binary-0.5.56.dist-info/WHEEL
gllm_datastore_binary-0.5.56.dist-info/top_level.txt
gllm_datastore_binary-0.5.56.dist-info/RECORD
