Metadata-Version: 2.2
Name: gllm-datastore-binary
Version: 0.5.56
Summary: A library containing data store components for Gen AI applications.
Author-email: Berty C L Tobing <berty.c.l.tobing@gdplabs.id>, Kadek Denaya <kadek.d.r.diana@gdplabs.id>
Requires-Python: <3.13,>=3.11
Requires-Dist: gllm-core-binary<0.5.0,>=0.3.0
Requires-Dist: gllm-inference-binary<0.6.0,>=0.5.0
Requires-Dist: cryptography<44.0.0,>=43.0.3
Requires-Dist: nebula3-python<4.0.0,>=3.8.3
Requires-Dist: neo4j<6.0.0,>=5.28.1
Requires-Dist: nest-asyncio==1.6.0
Requires-Dist: pandas<3.0.0,>=2.2.3
Requires-Dist: pysqlite3-binary<0.6.0,>=0.5.4; sys_platform == "linux"
Requires-Dist: sqlalchemy<3.0.0,>=2.0.37
Requires-Dist: python-levenshtein<0.27.0,>=0.26.1
Requires-Dist: urllib3<3.0.0,>=2.6.0
Requires-Dist: langchain-core<0.4.0,>=0.3.81
Provides-Extra: dev
Requires-Dist: coverage<8.0.0,>=7.4.4; extra == "dev"
Requires-Dist: mypy<2.0.0,>=1.15.0; extra == "dev"
Requires-Dist: pre-commit<4.0.0,>=3.7.0; extra == "dev"
Requires-Dist: pytest<9.0.0,>=8.1.1; extra == "dev"
Requires-Dist: pytest-asyncio<1.0.0,>=0.23.6; extra == "dev"
Requires-Dist: pytest-cov<6.0.0,>=5.0.0; extra == "dev"
Requires-Dist: ruff<1.0.0,>=0.6.7; extra == "dev"
Provides-Extra: chroma
Requires-Dist: chromadb<0.7.0,>=0.6.3; extra == "chroma"
Requires-Dist: langchain-chroma<0.3.0,>=0.2.2; extra == "chroma"
Requires-Dist: posthog<6.0.0,>=2.4.0; extra == "chroma"
Provides-Extra: elasticsearch
Requires-Dist: elasticsearch<8.20.0,>=8.19.0; extra == "elasticsearch"
Requires-Dist: langchain-elasticsearch<0.4.0,>=0.3.0; extra == "elasticsearch"
Provides-Extra: fuzzy
Provides-Extra: kg
Requires-Dist: asyncpg<0.31.0,>=0.30.0; extra == "kg"
Requires-Dist: Jinja2<4.0.0,>=3.1.4; extra == "kg"
Requires-Dist: lightrag-hku<1.4.9.8,>=1.4.6; extra == "kg"
Requires-Dist: llama-index-core<0.15.0,>=0.14.0; extra == "kg"
Requires-Dist: llama-index-graph-stores-nebula<0.6.0,>=0.5.0; extra == "kg"
Requires-Dist: llama-index-graph-stores-neo4j<0.6.0,>=0.5.0; extra == "kg"
Provides-Extra: redis
Requires-Dist: redis<6.0.0,>=5.2.1; extra == "redis"
Requires-Dist: redisvl[sentence-transformers]<0.7.0,>=0.6.0; extra == "redis"
Requires-Dist: torch<3.0.0,>2.0.0; extra == "redis"
Provides-Extra: opensearch
Requires-Dist: opensearch-py[async]<3.0.0,>=2.0.0; extra == "opensearch"
Requires-Dist: langchain-community<0.4.0,>=0.3.0; extra == "opensearch"
Provides-Extra: milvus
Requires-Dist: pymilvus<3.0.0,>=2.6.6; extra == "milvus"
